pypsf/__init__.py
pypsf/clustering.py
pypsf/hyperparameter_search.py
pypsf/neighbors.py
pypsf/predict.py
pypsf/psf.py
pypsf/utils.py
pypsf-1.0.9.dist-info/METADATA
pypsf-1.0.9.dist-info/WHEEL
pypsf-1.0.9.dist-info/licenses/LICENSE
pypsf-1.0.9.dist-info/RECORD
