Metadata-Version: 2.4
Name: pypsf
Version: 1.0.9
Summary: Python implementation of the Pattern Sequence Based Forecasting (PSF) algorithm
Project-URL: Homepage, https://github.com/mamei16/PyPSF
Project-URL: Bug Tracker, https://github.com/mamei16/PyPSF/issues
Author: Marcel Meimbresse
License: MIT License Copyright (c) 2020 Marcel Meimbresse
License-File: LICENSE
Classifier: License :: OSI Approved :: MIT License
Classifier: Operating System :: OS Independent
Classifier: Programming Language :: Python :: 3
Requires-Python: >=3.7
Requires-Dist: numpy>=1.21
Requires-Dist: scikit-learn>=1.0
